reactivetools/__init__.py
reactivetools/py.typed
reactivetools-0.1.0.dist-info/LICENSE
reactivetools-0.1.0.dist-info/WHEEL
reactivetools-0.1.0.dist-info/METADATA
reactivetools-0.1.0.dist-info/RECORD
